saber/__init__.py
saber/benchmark.py
saber/config.py
saber/engine.py
saber/llm_config.py
saber/query_generator.py
saber_query-0.5.0.dist-info/licenses/LICENSE
saber_query-0.5.0.dist-info/METADATA
saber_query-0.5.0.dist-info/WHEEL
saber_query-0.5.0.dist-info/top_level.txt
saber_query-0.5.0.dist-info/RECORD
