Metadata-Version: 2.4
Name: saber-query
Version: 0.5.0
Summary: SABER: A SQL-Compatible Semantic Document Processing System Based on Extended Relational Algebra
Author-email: Changjae Lee <changjae@buffalo.edu>
Maintainer-email: Changjae Lee <changjae@buffalo.edu>
License: Copyright (c) 2025-present, Changjae Lee 
Project-URL: Homepage, https://github.com/xlab-ub/saber
Project-URL: Repository, https://github.com/xlab-ub/saber.git
Project-URL: Documentation, https://github.com/xlab-ub/saber
Project-URL: Issues, https://github.com/xlab-ub/saber/issues
Keywords: database,sql,semantic,ai,llm,query,lotus,docetl,palimpzest
Classifier: Development Status :: 3 - Alpha
Classifier: Intended Audience :: Science/Research
Classifier: Intended Audience :: Developers
Classifier: Programming Language :: Python :: 3
Classifier: Programming Language :: Python :: 3.12
Requires-Python: <3.13,>=3.12
License-File: LICENSE
Requires-Dist: openai>=1.0.0
Requires-Dist: duckdb>=1.3.2
Requires-Dist: sqlglotrs>=0.7.3
Requires-Dist: sqlglot>=27.27.0
Requires-Dist: lotus-ai>=1.1.3
Requires-Dist: docetl>=0.2.4
Requires-Dist: mysql-connector-python>=9.5.0
Requires-Dist: sqlalchemy>=2.0.0
Provides-Extra: lotus
Requires-Dist: lotus-ai>=1.1.3; extra == "lotus"
Provides-Extra: docetl
Requires-Dist: docetl>=0.2.4; extra == "docetl"
Provides-Extra: palimpzest
Requires-Dist: palimpzest>=1.1.0; extra == "palimpzest"
Provides-Extra: all
Requires-Dist: lotus-ai>=1.1.3; extra == "all"
Requires-Dist: docetl>=0.2.4; extra == "all"
Requires-Dist: palimpzest>=1.1.0; extra == "all"
Dynamic: license-file
